dnspx/__init__.py
dnspx/__main__.py
dnspx/cli.py
dnspx/config.py
dnspx/core.py
dnspx/error.py
dnspx/log.py
dnspx/resolve.py
dnspx/utils.py
dnspx/version.py
dnspx-0.1.9.dist-info/METADATA
dnspx-0.1.9.dist-info/WHEEL
dnspx-0.1.9.dist-info/entry_points.txt
dnspx-0.1.9.dist-info/top_level.txt
dnspx-0.1.9.dist-info/RECORD
